Metadata-Version: 2.4
Name: large-image-source-openslide
Version: 1.34.0
Summary: An Openslide tilesource for large_image.
Home-page: https://github.com/girder/large_image
Author: Kitware, Inc.
Author-email: kitware@kitware.com
License: Apache-2.0
Keywords: large_image,tile source
Classifier: Development Status :: 5 - Production/Stable
Classifier: Programming Language :: Python :: 3
Classifier: Programming Language :: Python :: 3.10
Classifier: Programming Language :: Python :: 3.11
Classifier: Programming Language :: Python :: 3.12
Classifier: Programming Language :: Python :: 3.13
Classifier: Programming Language :: Python :: 3.14
Requires-Python: >=3.10
License-File: LICENSE
Requires-Dist: large-image>=1.34.0
Requires-Dist: openslide-python>=1.4.1
Requires-Dist: openslide-bin; platform_system == "Linux" and platform_machine == "x86_64"
Requires-Dist: openslide-bin; platform_system == "Linux" and platform_machine == "aarch64"
Requires-Dist: openslide-bin; platform_system == "Windows" and platform_machine == "AMD64"
Requires-Dist: openslide-bin; platform_system == "Darwin" and platform_machine == "arm64"
Requires-Dist: openslide-bin; platform_system == "Darwin" and platform_machine == "x86_64"
Requires-Dist: tifftools>=1.7.0
Provides-Extra: girder
Requires-Dist: girder-large-image>=1.34.0; extra == "girder"
Dynamic: author
Dynamic: author-email
Dynamic: classifier
Dynamic: description
Dynamic: description-content-type
Dynamic: home-page
Dynamic: keywords
Dynamic: license
Dynamic: license-file
Dynamic: provides-extra
Dynamic: requires-dist
Dynamic: requires-python
Dynamic: summary
